tados/__init__.py
tados-0.0.1.dist-info/METADATA
tados-0.0.1.dist-info/WHEEL
tados-0.0.1.dist-info/top_level.txt
tados-0.0.1.dist-info/RECORD
